taru/__init__.py
taru/cli.py
taru-1.0.4.data/data/share/man/man1/taru.1
taru-1.0.4.dist-info/METADATA
taru-1.0.4.dist-info/WHEEL
taru-1.0.4.dist-info/entry_points.txt
taru-1.0.4.dist-info/top_level.txt
taru-1.0.4.dist-info/RECORD
