Metadata-Version: 2.1
Name: taru
Version: 1.0.4
Summary: Taru processes a tar listing to display the cumulative size of files stored in individual directories.
Home-page: https://github.com/dspinellis/taru
Author: Diomidis Spinellis
Author-email: dds@aueb.gr
License: Apache Software License
Keywords: tar,du,size
Platform: any
Classifier: Development Status :: 5 - Production/Stable
Classifier: Environment :: Console
Classifier: Intended Audience :: Developers
Classifier: License :: OSI Approved :: Apache Software License
Classifier: Operating System :: POSIX
Classifier: Operating System :: MacOS
Classifier: Operating System :: Unix
Classifier: Operating System :: Microsoft :: Windows
Classifier: Programming Language :: Python
Classifier: Programming Language :: Python :: 3
Classifier: Topic :: System :: Archiving
Classifier: Topic :: Utilities
